managerx_handler-1.2026.1.10.dist-info/licenses/LICENSE
mx_handler/__init__.py
mx_handler/translation_handler.py
mx_handler/update_checker.py
mx_handler/utils.py
managerx_handler-1.2026.1.10.dist-info/METADATA
managerx_handler-1.2026.1.10.dist-info/WHEEL
managerx_handler-1.2026.1.10.dist-info/top_level.txt
managerx_handler-1.2026.1.10.dist-info/RECORD
