Metadata-Version: 2.4
Name: ManagerX-Handler
Version: 1.2026.1.10
Summary: Comprehensive handler library for Discord bots built with py-cord [ManagerX Ecosystem]
Author-email: "OPPRO.NET Development" <development@oppro-network.de>
License: GPL-3.0-or-later
Project-URL: Homepage, https://github.com/Oppro-net-Development/ManagerX-Handler
Project-URL: Documentation, https://docs.oppro.net/managerx-handler
Project-URL: Repository, https://github.com/Oppro-net-Development/ManagerX-Handler
Project-URL: Issues, https://github.com/Oppro-net-Development/ManagerX-Handler/issues
Keywords: discord,bot,py-cord,translation,handler,i18n
Classifier: Development Status :: 4 - Beta
Classifier: Intended Audience :: Developers
Classifier: License :: OSI Approved :: GNU General Public License v3 or later (GPLv3+)
Classifier: Programming Language :: Python :: 3
Classifier: Programming Language :: Python :: 3.8
Classifier: Programming Language :: Python :: 3.9
Classifier: Programming Language :: Python :: 3.10
Classifier: Programming Language :: Python :: 3.11
Classifier: Programming Language :: Python :: 3.12
Classifier: Programming Language :: Python :: 3.13
Classifier: Framework :: AsyncIO
Classifier: Topic :: Software Development :: Libraries :: Python Modules
Requires-Python: >=3.8
License-File: LICENSE
Requires-Dist: aiohttp>=3.9.0
Requires-Dist: pyyaml>=6.0
Requires-Dist: py-cord>=2.6.0
Requires-Dist: colorama>=0.4.6
Provides-Extra: dev
Requires-Dist: pytest>=7.4.0; extra == "dev"
Requires-Dist: pytest-asyncio>=0.21.0; extra == "dev"
Requires-Dist: black>=23.0.0; extra == "dev"
Requires-Dist: mypy>=1.5.0; extra == "dev"
Requires-Dist: ruff>=0.1.0; extra == "dev"
Dynamic: license-file
